Metadata-Version: 2.1
Name: EasyNMT
Version: 2.0.2
Summary: Easy to use state-of-the-art Neural Machine Translation
Home-page: https://github.com/UKPLab/EasyNMT
Download-URL: https://github.com/UKPLab/EasyNMT/archive/v2.0.2.zip
Author: Nils Reimers
Author-email: info@nils-reimers.de
License: Apache License 2.0
Keywords: Neural Machine Translation
Platform: UNKNOWN
Classifier: Development Status :: 4 - Beta
Classifier: Intended Audience :: Science/Research
Classifier: License :: OSI Approved :: Apache Software License
Classifier: Programming Language :: Python :: 3.7
Classifier: Topic :: Scientific/Engineering :: Artificial Intelligence
License-File: LICENSE
License-File: NOTICE.txt
